emd/pipeline/s5cmd
emd/__init__.py
emd/cfn/codepipeline/template.yaml
emd/cfn/ec2/template.yaml
emd/cfn/ecs/cluster.yaml
emd/cfn/ecs/post_build.py
emd/cfn/ecs/template.yaml
emd/cfn/sagemaker/template.yaml
emd/cfn/sagemaker_async/template.yaml
emd/cfn/vpc/template.yaml
emd/cli.py
emd/commands/bootstrap.py
emd/commands/config.py
emd/commands/deploy.py
emd/commands/destroy.py
emd/commands/invoke/invoke.py
emd/commands/status.py
emd/commands/version.py
emd/constants.py
emd/integrations/langchain_clients.py
emd/models/README.md
emd/models/__init__.py
emd/models/asr/__init__.py
emd/models/asr/whisper.py
emd/models/chat_templates/deepseek_r1.jinja
emd/models/chat_templates/deepseek_r1_distill.jinja
emd/models/chat_templates/internlm2d5_add_prefill_chat_template.jinja
emd/models/chat_templates/llama3d3_add_prefill_chat_templates copy.jinja
emd/models/chat_templates/llama3d3_add_prefill_chat_templates.jinja
emd/models/chat_templates/qwen2vl_add_prefill_chat_template.jinja
emd/models/chat_templates/qwen_2d5_add_prefill_chat_template.jinja
emd/models/comfyui/__init__.py
emd/models/comfyui/comfyui.py
emd/models/embeddings/__init__.py
emd/models/embeddings/bert_embedding.py
emd/models/engines.py
emd/models/frameworks.py
emd/models/instances.py
emd/models/llms/__init__.py
emd/models/llms/baichuan.py
emd/models/llms/deepseek.py
emd/models/llms/glm.py
emd/models/llms/internlm.py
emd/models/llms/llama.py
emd/models/llms/qwen.py
emd/models/model.py
emd/models/model_series.py
emd/models/reranks/__init__.py
emd/models/reranks/bge.py
emd/models/services.py
emd/models/utils/constants.py
emd/models/utils/logger_utils.py
emd/models/utils/model_files_modify_hooks.py
emd/models/utils/serialize_utils.py
emd/models/utils/text_utilities.py
emd/models/vlms/__init__.py
emd/models/vlms/internvl.py
emd/models/vlms/qwen.py
emd/patch_questionary/common_with_help.py
emd/patch_questionary/select_with_help.py
emd/revision.py
emd/sample/vlm_sample_data.jpg
emd/sdk/bootstrap.py
aws_emd-0.7.0.dist-info/LICENSE
aws_emd-0.7.0.dist-info/METADATA
aws_emd-0.7.0.dist-info/WHEEL
aws_emd-0.7.0.dist-info/entry_points.txt
aws_emd-0.7.0.dist-info/RECORD
