Metadata-Version: 2.3
Name: aws-emd
Version: 0.7.0
Summary: Deploy Model Anywhere on AWS
Author: Yi Yan
Author-email: yiyanz@amazon.com
Requires-Python: >=3.9,<4.0
Classifier: License :: OSI Approved :: MIT License
Classifier: Operating System :: OS Independent
Classifier: Programming Language :: Python :: 3
Classifier: Programming Language :: Python :: 3.9
Classifier: Programming Language :: Python :: 3.10
Classifier: Programming Language :: Python :: 3.11
Classifier: Programming Language :: Python :: 3.12
Classifier: Programming Language :: Python :: 3.13
Requires-Dist: boto3 (>=1.35.0,<2.0.0)
Requires-Dist: huggingface_hub (>=0.26.1,<0.27.0)
Requires-Dist: jinja2 (>=3.1.4,<4.0.0)
Requires-Dist: langchain (>=0.3.9,<0.4.0)
Requires-Dist: langchain-aws (>=0.2.13,<0.3.0)
Requires-Dist: modelscope (>=1.21.1,<2.0.0)
Requires-Dist: openai (>=1.54.4,<2.0.0)
Requires-Dist: pydantic (>=2.9.2,<3.0.0)
Requires-Dist: questionary (>=2.0.1,<3.0.0)
Requires-Dist: requests (>=2.26,<3.0)
Requires-Dist: rich (>=13.9.4,<14.0.0)
Requires-Dist: sagemaker (>=2.237.0,<3.0.0)
Requires-Dist: typer[all] (>=0.13.0,<0.14.0)
